fastapi_elasticsearch_middleware/__init__.py
fastapi_elasticsearch_middleware/elasticsearch_middleware.py
fastapi_elasticsearch_middleware-1.1.3.dist-info/LICENSE
fastapi_elasticsearch_middleware-1.1.3.dist-info/METADATA
fastapi_elasticsearch_middleware-1.1.3.dist-info/WHEEL
fastapi_elasticsearch_middleware-1.1.3.dist-info/top_level.txt
fastapi_elasticsearch_middleware-1.1.3.dist-info/RECORD
