Metadata-Version: 2.1
Name: fastapi_elasticsearch_middleware
Version: 1.1.3
Summary: Elasticsearch Logger Middleware for FastAPI
Home-page: https://github.com/GGontijo/fastapi-elasticsearch-middleware.git
Author: Gabriel Gontijo
Author-email: gabrieldercilio08@gmail.com
Keywords: python,middleware,fastapi,elasticsearch,kibana,logstash,fastapi-middleware
Classifier: Programming Language :: Python :: 3
Classifier: License :: OSI Approved :: MIT License
Classifier: Operating System :: OS Independent
Classifier: Development Status :: 4 - Beta
Classifier: Intended Audience :: Developers
Classifier: Topic :: Software Development :: Libraries :: Python Modules
Classifier: Topic :: Internet :: WWW/HTTP :: HTTP Servers
License-File: LICENSE
Requires-Dist: fastapi
Requires-Dist: elasticsearch
